yummy_features-0.0.9.dist-info/METADATA
yummy_features-0.0.9.dist-info/WHEEL
yummy_features-0.0.9.dist-info/license_files/LICENSE
yummy_features.libs/libcrypto-75174c47.so.1.1
yummy_features.libs/libssl-f8da170d.so.1.1
yummy_features/__init__.py
yummy_features/yummy_features.cpython-39-x86_64-linux-gnu.so
yummy_features-0.0.9.dist-info/RECORD
