Metadata-Version: 2.1
Name: yummy-features
Version: 0.0.9
Classifier: Programming Language :: Rust
Classifier: Programming Language :: Python :: Implementation :: CPython
Classifier: Programming Language :: Python :: Implementation :: PyPy
License-File: LICENSE
Summary: Yummy feature store server
License: Apache-2.0
Requires-Python: >=3.7
Project-URL: repository, https://github.com/yummyml/yummy
